<annotation>
    <folder>output</folder>
    <filename>000658.png</filename>
    <path>/home/kam/carla_packed_linux/CARLA_0.9.16/ee267-fall25-lab0-team-3/output/000658.png</path>
    <source>
        <database>Unknown</database>
    </source>
    <size>
        <width>800</width>
        <height>600</height>
        <depth>3</depth>
    </size>
    <segmented>0</segmented>
    <object>
        <name>vehicle</name>
        <pose>Unspecified</pose>
        <truncated>0</truncated>
        <difficult>0</difficult>
        <bndbox>
            <xmin>746</xmin>
            <ymin>310</ymin>
            <xmax>789</xmax>
            <ymax>343</ymax>
        </bndbox>
    </object>    <object>
        <name>vehicle</name>
        <pose>Unspecified</pose>
        <truncated>0</truncated>
        <difficult>0</difficult>
        <bndbox>
            <xmin>664</xmin>
            <ymin>310</ymin>
            <xmax>739</xmax>
            <ymax>329</ymax>
        </bndbox>
    </object>
</annotation>
